flyre.pyw
readme.md
src/__init__.py
src/level.py
src/assets/settings.json
src/assets/animations/bomb.json
src/assets/animations/explosion.json
src/assets/animations/explosion1.json
src/assets/animations/explosion2.json
src/assets/animations/planet0.json
src/assets/animations/planet1.json
src/assets/animations/planet10.json
src/assets/animations/planet11.json
src/assets/animations/planet12.json
src/assets/animations/planet13.json
src/assets/animations/planet14.json
src/assets/animations/planet15.json
src/assets/animations/planet16.json
src/assets/animations/planet17.json
src/assets/animations/planet18.json
src/assets/animations/planet19.json
src/assets/animations/planet2.json
src/assets/animations/planet20.json
src/assets/animations/planet3.json
src/assets/animations/planet4.json
src/assets/animations/planet5.json
src/assets/animations/planet6.json
src/assets/animations/planet7.json
src/assets/animations/planet8.json
src/assets/animations/planet9.json
src/assets/fonts/Aerologica.ttf
src/assets/fonts/ThaleahFat.ttf
src/assets/fonts/Wellbutrin.ttf
src/assets/fonts/info.txt
src/assets/fonts/pixelmillennium.ttf
src/assets/images/bomb.ase
src/assets/images/bomb.png
src/assets/images/explosion1.png
src/assets/images/inforect.ase
src/assets/images/inforect.png
src/assets/images/planet0.png
src/assets/images/planet1.png
src/assets/images/planet10.png
src/assets/images/planet11.png
src/assets/images/planet12.png
src/assets/images/planet13.png
src/assets/images/planet14.png
src/assets/images/planet15.png
src/assets/images/planet16.png
src/assets/images/planet17.png
src/assets/images/planet18.png
src/assets/images/planet19.png
src/assets/images/planet2.png
src/assets/images/planet20.png
src/assets/images/planet3.png
src/assets/images/planet4.png
src/assets/images/planet5.png
src/assets/images/planet6.png
src/assets/images/planet7.png
src/assets/images/planet8.png
src/assets/images/planet9.png
src/assets/images/spaceships.ase
src/assets/images/spaceships.png
flyre-1.0.1.dist-info/METADATA
flyre-1.0.1.dist-info/WHEEL
flyre-1.0.1.dist-info/RECORD
