Metadata-Version: 2.4
Name: Flyre
Version: 1.0.1
Summary: A pixel art shooter with a skill tree.(DLC version)
Author-email: ddorn <diego.dorn@free.fr>, mark4d4 <sevcow4674@gmail.com>
License-Expression: MIT
